pquery/__init__.py
pquery/_pquery.py
pquery/_stats.py
pquery/py.typed
pqery-0.2.0.dist-info/METADATA
pqery-0.2.0.dist-info/WHEEL
pqery-0.2.0.dist-info/licenses/LICENSE
pqery-0.2.0.dist-info/RECORD
