Metadata-Version: 2.4
Name: pqery
Version: 0.2.0
Summary: A query like syntax for python Path objects.
Project-URL: Homepage, https://github.com/hucker/pquery
Project-URL: Documentation, https://github.com/hucker/pquery#readme
Project-URL: Repository, https://github.com/hucker/pquery.git
Project-URL: Bug Tracker, https://github.com/hucker/pquery/issues
Project-URL: Changelog, https://github.com/hucker/pquery/blob/main/CHANGELOG.md
Author-email: Your Name <your.email@example.com>
Maintainer-email: Your Name <your.email@example.com>
License: MIT
License-File: LICENSE
Keywords: age,file,lambda,pathlib,size,utility
Classifier: Development Status :: 3 - Alpha
Classifier: Intended Audience :: Developers
Classifier: License :: OSI Approved :: MIT License
Classifier: Operating System :: OS Independent
Classifier: Programming Language :: Python :: 3
Classifier: Programming Language :: Python :: 3.10
Classifier: Programming Language :: Python :: 3.11
Classifier: Programming Language :: Python :: 3.12
Classifier: Programming Language :: Python :: 3.13
Classifier: Programming Language :: Python :: 3.14
Classifier: Topic :: Software Development :: Libraries :: Python Modules
Classifier: Topic :: System :: Filesystems
Classifier: Topic :: Utilities
Classifier: Typing :: Typed
Requires-Python: >=3.10
Requires-Dist: tpath>=0.2.0
Provides-Extra: dev
Requires-Dist: coverage>=7.0; extra == 'dev'
Requires-Dist: mypy>=1.0; extra == 'dev'
Requires-Dist: pre-commit>=3.0; extra == 'dev'
Requires-Dist: pytest-cov>=4.0; extra == 'dev'
Requires-Dist: pytest>=7.0; extra == 'dev'
Requires-Dist: ruff>=0.1.0; extra == 'dev'
Provides-Extra: lint
Requires-Dist: mypy>=1.0; extra == 'lint'
Requires-Dist: ruff>=0.1.0; extra == 'lint'
Provides-Extra: test
Requires-Dist: pytest-cov>=4.0; extra == 'test'
Requires-Dist: pytest>=7.0; extra == 'test'
